{
  "$schema": "https://raw.githubusercontent.com/dotnet/core/release-index/release-notes/schemas/dotnet-release-timeline-index.json",
  "kind": "month-index",
  "title": ".NET Release Timeline Index - 2020-11",
  "description": "Release timeline for 2020-11 (latest: 5.0)",
  "year": "2020",
  "month": "11",
  "security": false,
  "latest_release": "5.0",
  "releases": [
    "5.0",
    "3.1"
  ],
  "_links": {
    "self": {
      "href": "https://raw.githubusercontent.com/dotnet/core/release-index/release-notes/timeline/2020/11/index.json",
      "path": "/timeline/2020/11/index.json",
      "title": "Release timeline index for 2020-11",
      "type": "application/hal\u002Bjson"
    },
    "next": {
      "href": "https://raw.githubusercontent.com/dotnet/core/release-index/release-notes/timeline/2020/12/index.json",
      "path": "/timeline/2020/12/index.json",
      "title": "Release timeline index for 2020-12",
      "type": "application/hal\u002Bjson"
    },
    "prev": {
      "href": "https://raw.githubusercontent.com/dotnet/core/release-index/release-notes/timeline/2020/10/index.json",
      "path": "/timeline/2020/10/index.json",
      "title": "Release timeline index for 2020-10",
      "type": "application/hal\u002Bjson"
    },
    "timeline-index": {
      "href": "https://raw.githubusercontent.com/dotnet/core/release-index/release-notes/timeline/index.json",
      "path": "/timeline/index.json",
      "title": ".NET Release Timeline Index",
      "type": "application/hal\u002Bjson"
    },
    "year-index": {
      "href": "https://raw.githubusercontent.com/dotnet/core/release-index/release-notes/timeline/2020/index.json",
      "path": "/timeline/2020/index.json",
      "title": ".NET Release Timeline Index - 2020",
      "type": "application/hal\u002Bjson"
    }
  },
  "_embedded": {
    "releases": [
      {
        "version": "5.0",
        "release_type": "sts",
        "phase": "active",
        "supported": false,
        "security": false,
        "cve_count": 0,
        "ga_date": "2020-11-10T00:00:00\u002B00:00",
        "eol_date": "2022-05-10T00:00:00\u002B00:00",
        "runtime_patches": [
          "5.0.0"
        ],
        "sdk_patches": [
          "5.0.100"
        ],
        "_links": {
          "self": {
            "href": "https://raw.githubusercontent.com/dotnet/core/release-index/release-notes/5.0/index.json",
            "path": "/5.0/index.json",
            "title": ".NET 5.0",
            "type": "application/hal\u002Bjson"
          },
          "release-patch": {
            "href": "https://raw.githubusercontent.com/dotnet/core/release-index/release-notes/5.0/5.0.0/index.json",
            "path": "/5.0/5.0.0/index.json",
            "title": ".NET 5.0.0",
            "type": "application/hal\u002Bjson"
          }
        }
      },
      {
        "version": "3.1",
        "release_type": "lts",
        "phase": "active",
        "supported": false,
        "security": false,
        "cve_count": 0,
        "ga_date": "2019-12-03T00:00:00\u002B00:00",
        "eol_date": "2022-12-13T00:00:00\u002B00:00",
        "runtime_patches": [
          "3.1.10"
        ],
        "sdk_patches": [
          "3.1.404",
          "3.1.110"
        ],
        "_links": {
          "self": {
            "href": "https://raw.githubusercontent.com/dotnet/core/release-index/release-notes/3.1/index.json",
            "path": "/3.1/index.json",
            "title": ".NET 3.1",
            "type": "application/hal\u002Bjson"
          },
          "release-patch": {
            "href": "https://raw.githubusercontent.com/dotnet/core/release-index/release-notes/3.1/3.1.10/index.json",
            "path": "/3.1/3.1.10/index.json",
            "title": ".NET 3.1.10",
            "type": "application/hal\u002Bjson"
          }
        }
      }
    ]
  },
  "_metadata": {
    "schema_version": "1.0",
    "generated_on": "2025-12-01T05:09:45.4219896\u002B00:00",
    "generated_by": "ShipIndex"
  }
}
