{
  "$schema": "https://raw.githubusercontent.com/dotnet/core/refs/heads/release-index/release-notes/schemas/v1/dotnet-patch-detail-index.json",
  "kind": "patch-version-index",
  "title": ".NET Patch Release Index - 5.0.4",
  "version": "5.0.4",
  "date": "2021-03-09T00:00:00\u002B00:00",
  "support_phase": "eol",
  "security": true,
  "cve_count": 1,
  "_links": {
    "self": {
      "href": "https://raw.githubusercontent.com/dotnet/core/refs/heads/release-index/release-notes/5.0/5.0.4/index.json"
    },
    "prev": {
      "href": "https://raw.githubusercontent.com/dotnet/core/refs/heads/release-index/release-notes/5.0/5.0.3/index.json",
      "title": "Previous patch release - 5.0.3"
    },
    "prev-security": {
      "href": "https://raw.githubusercontent.com/dotnet/core/refs/heads/release-index/release-notes/5.0/5.0.3/index.json",
      "title": "Previous security patch release - 5.0.3"
    },
    "release-major": {
      "href": "https://raw.githubusercontent.com/dotnet/core/refs/heads/release-index/release-notes/5.0/index.json",
      "title": ".NET Major Release Index - 5.0"
    },
    "release-manifest": {
      "href": "https://raw.githubusercontent.com/dotnet/core/refs/heads/release-index/release-notes/5.0/5.0.4/manifest.json",
      "title": "Manifest - .NET 5.0"
    },
    "release-month": {
      "href": "https://raw.githubusercontent.com/dotnet/core/refs/heads/release-index/release-notes/timeline/2021/03/index.json",
      "title": ".NET Month Timeline Index - March 2021"
    },
    "releases-index": {
      "href": "https://raw.githubusercontent.com/dotnet/core/refs/heads/release-index/release-notes/index.json",
      "title": ".NET Release Index"
    }
  }
}
