{
  "$schema": "https://raw.githubusercontent.com/dotnet/core/refs/heads/release-index/release-notes/schemas/v1/dotnet-patch-detail-index.json",
  "kind": "patch",
  "title": ".NET Patch Release Index - 2.1.5",
  "version": "2.1.5",
  "date": "2018-10-02T00:00:00\u002B00:00",
  "support_phase": "active",
  "security": false,
  "prev_patch_date": "2018-09-11T00:00:00\u002B00:00",
  "prev_security_patch_date": "2018-09-11T00:00:00\u002B00:00",
  "_links": {
    "self": {
      "href": "https://raw.githubusercontent.com/dotnet/core/refs/heads/release-index/release-notes/2.1/2.1.5/index.json"
    },
    "prev-patch": {
      "href": "https://raw.githubusercontent.com/dotnet/core/refs/heads/release-index/release-notes/2.1/2.1.4/index.json",
      "title": "Previous patch release - 2.1.4"
    },
    "prev-security-patch": {
      "href": "https://raw.githubusercontent.com/dotnet/core/refs/heads/release-index/release-notes/2.1/2.1.4/index.json",
      "title": "Previous security patch release - 2.1.4"
    },
    "major": {
      "href": "https://raw.githubusercontent.com/dotnet/core/refs/heads/release-index/release-notes/2.1/index.json",
      "title": ".NET Major Release Index - 2.1"
    },
    "month": {
      "href": "https://raw.githubusercontent.com/dotnet/core/refs/heads/release-index/release-notes/timeline/2018/10/index.json",
      "title": ".NET Month Timeline Index - October 2018"
    },
    "root": {
      "href": "https://raw.githubusercontent.com/dotnet/core/refs/heads/release-index/release-notes/index.json",
      "title": ".NET Release Index"
    }
  }
}
