{
  "$schema": "https://raw.githubusercontent.com/dotnet/core/4b3e8b0817034a3142e36e3f3ea1a0408cc6a5e2/release-notes/schemas/dotnet-release-timeline-index.json",
  "kind": "timeline-month-index",
  "title": ".NET Release Timeline Index - 2018-09",
  "description": "Release timeline for 2018-09 (2.1\u20132.2, latest first); This file is cache-friendly; follow links for the most current details.",
  "year": "2018",
  "month": "09",
  "_links": {
    "self": {
      "href": "https://raw.githubusercontent.com/dotnet/core/4b3e8b0817034a3142e36e3f3ea1a0408cc6a5e2/release-notes/timeline/2018/09/index.json",
      "relative": "timeline/2018/09/index.json",
      "title": "Release timeline index for 2018-09",
      "type": "application/hal\u002Bjson"
    },
    "prev": {
      "href": "https://raw.githubusercontent.com/dotnet/core/4b3e8b0817034a3142e36e3f3ea1a0408cc6a5e2/release-notes/timeline/2018/08/index.json",
      "relative": "timeline/2018/08/index.json",
      "title": "Release timeline index for 2018-08",
      "type": "application/hal\u002Bjson"
    },
    "next": {
      "href": "https://raw.githubusercontent.com/dotnet/core/4b3e8b0817034a3142e36e3f3ea1a0408cc6a5e2/release-notes/timeline/2018/10/index.json",
      "relative": "timeline/2018/10/index.json",
      "title": "Release timeline index for 2018-10",
      "type": "application/hal\u002Bjson"
    }
  },
  "_embedded": {
    "releases": {
      "2.2": {
        "patches": {
          "dotnet-runtime": [
            "2.2.0-preview2-26905-02"
          ]
        },
        "_links": {
          "version-index": {
            "href": "https://raw.githubusercontent.com/dotnet/core/4b3e8b0817034a3142e36e3f3ea1a0408cc6a5e2/release-notes/2.2/index.json",
            "relative": "2.2/index.json",
            "title": ".NET 2.2 Version Index",
            "type": "application/hal\u002Bjson"
          },
          "2.2.0-preview2-26905-02": {
            "href": "https://raw.githubusercontent.com/dotnet/core/4b3e8b0817034a3142e36e3f3ea1a0408cc6a5e2/release-notes/2.2/2.2.0-preview2/release.json",
            "relative": "2.2/2.2.0-preview2/release.json",
            "title": ".NET 2.2.0-preview2-26905-02 Release",
            "type": "application/json"
          },
          "2.2.0-preview2-26905-02-markdown-raw": {
            "href": "https://raw.githubusercontent.com/dotnet/core/4b3e8b0817034a3142e36e3f3ea1a0408cc6a5e2/release-notes/2.2/2.2.0-preview2/README.md",
            "relative": "2.2/2.2.0-preview2/README.md",
            "title": ".NET 2.2.0-preview2-26905-02 Release Notes (Raw Markdown)",
            "type": "application/markdown"
          }
        }
      },
      "2.1": {
        "patches": {
          "dotnet-runtime": [
            "2.1.4"
          ]
        },
        "_links": {
          "version-index": {
            "href": "https://raw.githubusercontent.com/dotnet/core/4b3e8b0817034a3142e36e3f3ea1a0408cc6a5e2/release-notes/2.1/index.json",
            "relative": "2.1/index.json",
            "title": ".NET 2.1 Version Index",
            "type": "application/hal\u002Bjson"
          },
          "2.1.4": {
            "href": "https://raw.githubusercontent.com/dotnet/core/4b3e8b0817034a3142e36e3f3ea1a0408cc6a5e2/release-notes/2.1/2.1.4/release.json",
            "relative": "2.1/2.1.4/release.json",
            "title": ".NET 2.1.4 Release",
            "type": "application/json"
          },
          "2.1.4-markdown-raw": {
            "href": "https://raw.githubusercontent.com/dotnet/core/4b3e8b0817034a3142e36e3f3ea1a0408cc6a5e2/release-notes/2.1/2.1.4/README.md",
            "relative": "2.1/2.1.4/README.md",
            "title": ".NET 2.1.4 Release Notes (Raw Markdown)",
            "type": "application/markdown"
          }
        }
      }
    }
  },
  "_metadata": {
    "schema-version": "1.0",
    "generated-on": "2025-11-13T23:19:57.8940387\u002B00:00",
    "generated-by": "ShipIndex"
  }
}
